lazyscraper/consts.py
lazyscraper/htmltools.py
lazyscraper/patterns.py
lazyscraper/scraper.py
lazyscraper/urltools.py
lazyscraper/__init__.py
lazyscraper-0.1.0.data/scripts/lscraper.py
lazyscraper-0.1.0.dist-info/DESCRIPTION.rst
lazyscraper-0.1.0.dist-info/METADATA
lazyscraper-0.1.0.dist-info/metadata.json
lazyscraper-0.1.0.dist-info/RECORD
lazyscraper-0.1.0.dist-info/top_level.txt
lazyscraper-0.1.0.dist-info/WHEEL
