Metadata-Version: 2.0
Name: lazyscraper
Version: 0.1.0
Summary: Lazy simple command line tool, a swiss knife for scraper writers. Automates scraping so much as possible
Home-page: https://github.com/ivbeg/lazyscraper
Author: Ivan Begtin
Author-email: ivan@begtin.tech
License: BSD
Keywords: scraping lazy lazy-scraping htmlpatterns
Platform: UNKNOWN
Classifier: Development Status :: 2 - Pre-Alpha
Classifier: Intended Audience :: Developers
Classifier: License :: OSI Approved :: BSD License
Classifier: Natural Language :: English
Classifier: Programming Language :: Python :: 3
Classifier: Programming Language :: Python :: 3.3
Classifier: Programming Language :: Python :: 3.4
Classifier: Programming Language :: Python :: 3.5
Classifier: Programming Language :: Python :: 3.6
Classifier: Programming Language :: Python :: Implementation :: CPython
Classifier: Programming Language :: Python :: Implementation :: PyPy
Requires-Dist: lxml
Requires-Dist: click
